./.gitignore
./PKG-INFO
./README.md
./pyproject.toml
./vision_agents/plugins/elevenlabs/__init__.py
./vision_agents/plugins/elevenlabs/stt.py
./vision_agents/plugins/elevenlabs/tts.py
vision_agents/plugins/elevenlabs/__init__.py
vision_agents/plugins/elevenlabs/stt.py
vision_agents/plugins/elevenlabs/tts.py
vision_agents_plugins_elevenlabs-0.2.10.dist-info/METADATA
vision_agents_plugins_elevenlabs-0.2.10.dist-info/WHEEL
vision_agents_plugins_elevenlabs-0.2.10.dist-info/RECORD
