Metadata-Version: 2.4
Name: vision-agents-plugins-elevenlabs
Version: 0.2.10
Summary: ElevenLabs TTS and STT integration for Vision Agents
Project-URL: Documentation, https://visionagents.ai/
Project-URL: Website, https://visionagents.ai/
Project-URL: Source, https://github.com/GetStream/Vision-Agents
License-Expression: MIT
Keywords: AI,STT,TTS,agents,elevenlabs,speech-to-text,text-to-speech,voice agents
Requires-Python: >=3.10
Requires-Dist: elevenlabs>=2.24.0
Requires-Dist: vision-agents
